{
    "sector_name": "Arzul",
    "sector_position": [
        3,
        -2
    ],
    "subsectors": [
        {
            "subsector_index": 1,
            "subsector_name": "Rraz"
        },
        {
            "subsector_index": 2,
            "subsector_name": "Kikhu"
        },
        {
            "subsector_index": 3,
            "subsector_name": "Voeraghz"
        },
        {
            "subsector_index": 4,
            "subsector_name": "Khefs Dzo"
        },
        {
            "subsector_index": 5,
            "subsector_name": "Gakhir"
        },
        {
            "subsector_index": 6,
            "subsector_name": "Kotsfa"
        },
        {
            "subsector_index": 7,
            "subsector_name": "Lekorma"
        },
        {
            "subsector_index": 8,
            "subsector_name": "Ghap Dall"
        },
        {
            "subsector_index": 9,
            "subsector_name": "Nishamidu"
        },
        {
            "subsector_index": 10,
            "subsector_name": "Gorzadi"
        },
        {
            "subsector_index": 11,
            "subsector_name": "Veldt"
        },
        {
            "subsector_index": 12,
            "subsector_name": "Prairie"
        },
        {
            "subsector_index": 13,
            "subsector_name": "Mycocona"
        },
        {
            "subsector_index": 14,
            "subsector_name": "Ambro"
        },
        {
            "subsector_index": 15,
            "subsector_name": "Plains"
        },
        {
            "subsector_index": 16,
            "subsector_name": "Desert"
        }
    ],
    "systems": [
        {
            "system_name": "Rutagh",
            "system_position": [
                1,
                6
            ],
            "system_uwp": "E6A6112-9"
        },
        {
            "system_name": "Carrarn",
            "system_position": [
                1,
                9
            ],
            "system_uwp": "B100759-C"
        },
        {
            "system_name": "Khakarrgh",
            "system_position": [
                2,
                1
            ],
            "system_uwp": "B677737-9"
        },
        {
            "system_name": "Rahar",
            "system_position": [
                2,
                3
            ],
            "system_uwp": "C695634-5"
        },
        {
            "system_name": "Rrurrgur",
            "system_position": [
                2,
                6
            ],
            "system_uwp": "B311267-B"
        },
        {
            "system_name": "Agha",
            "system_position": [
                2,
                7
            ],
            "system_uwp": "C210635-D"
        },
        {
            "system_name": "Shaka",
            "system_position": [
                2,
                10
            ],
            "system_uwp": "C4455D7-A"
        },
        {
            "system_name": "Caska",
            "system_position": [
                3,
                3
            ],
            "system_uwp": "A765A9B-B"
        },
        {
            "system_name": "Khaz",
            "system_position": [
                3,
                5
            ],
            "system_uwp": "E68727B-1"
        },
        {
            "system_name": "Ghirrzik",
            "system_position": [
                3,
                7
            ],
            "system_uwp": "D210457-C"
        },
        {
            "system_name": "Cis-rabir",
            "system_position": [
                3,
                10
            ],
            "system_uwp": "B4957C9-C"
        },
        {
            "system_name": "Hebrar",
            "system_position": [
                4,
                2
            ],
            "system_uwp": "B6988B6-7"
        },
        {
            "system_name": "Ziraghur",
            "system_position": [
                4,
                5
            ],
            "system_uwp": "A99856A-C"
        },
        {
            "system_name": "Ghurrgarrgh",
            "system_position": [
                4,
                8
            ],
            "system_uwp": "C320558-B"
        },
        {
            "system_name": "Par",
            "system_position": [
                5,
                5
            ],
            "system_uwp": "A4639A5-A"
        },
        {
            "system_name": "Raub",
            "system_position": [
                6,
                1
            ],
            "system_uwp": "CAC4414-C"
        },
        {
            "system_name": "Ghukhakh",
            "system_position": [
                6,
                6
            ],
            "system_uwp": "E510300-2"
        },
        {
            "system_name": "Papaa",
            "system_position": [
                6,
                10
            ],
            "system_uwp": "C469436-7"
        },
        {
            "system_name": "Siraska",
            "system_position": [
                7,
                7
            ],
            "system_uwp": "D574524-A"
        },
        {
            "system_name": "Khurrgh",
            "system_position": [
                8,
                2
            ],
            "system_uwp": "B65A99C-8"
        },
        {
            "system_name": "Sikhi",
            "system_position": [
                8,
                3
            ],
            "system_uwp": "D8C3418-B"
        },
        {
            "system_name": "Canta",
            "system_position": [
                8,
                4
            ],
            "system_uwp": "D575A88-7"
        },
        {
            "system_name": "Rinkook",
            "system_position": [
                8,
                5
            ],
            "system_uwp": "CA7A543-A"
        },
        {
            "system_name": "Rurrzik",
            "system_position": [
                8,
                7
            ],
            "system_uwp": "C699343-5"
        },
        {
            "system_name": "Khaekhurr",
            "system_position": [
                8,
                10
            ],
            "system_uwp": "C444657-B"
        },
        {
            "system_name": "Saepar",
            "system_position": [
                9,
                4
            ],
            "system_uwp": "C000659-B"
        },
        {
            "system_name": "Ghueghik",
            "system_position": [
                9,
                5
            ],
            "system_uwp": "C634565-7"
        },
        {
            "system_name": "Voegan",
            "system_position": [
                9,
                9
            ],
            "system_uwp": "D312534-8"
        },
        {
            "system_name": "Rutarrgh",
            "system_position": [
                10,
                7
            ],
            "system_uwp": "A4519ED-8"
        },
        {
            "system_name": "Arrghan",
            "system_position": [
                10,
                8
            ],
            "system_uwp": "A476999-A"
        },
        {
            "system_name": "Tagh",
            "system_position": [
                11,
                2
            ],
            "system_uwp": "B1108C9-B"
        },
        {
            "system_name": "Dakh",
            "system_position": [
                11,
                8
            ],
            "system_uwp": "D689944-8"
        },
        {
            "system_name": "Digh",
            "system_position": [
                11,
                9
            ],
            "system_uwp": "A556785-8"
        },
        {
            "system_name": "Sezakh",
            "system_position": [
                12,
                2
            ],
            "system_uwp": "D777341-5"
        },
        {
            "system_name": "Errurrgh",
            "system_position": [
                12,
                3
            ],
            "system_uwp": "B895345-B"
        },
        {
            "system_name": "Rarrza",
            "system_position": [
                12,
                7
            ],
            "system_uwp": "B894846-9"
        },
        {
            "system_name": "Agodz",
            "system_position": [
                12,
                10
            ],
            "system_uwp": "B9867A8-8"
        },
        {
            "system_name": "Rudzkha",
            "system_position": [
                13,
                7
            ],
            "system_uwp": "A475420-D"
        },
        {
            "system_name": "Ragh",
            "system_position": [
                13,
                8
            ],
            "system_uwp": "A8B688A-B"
        },
        {
            "system_name": "Digharrgh",
            "system_position": [
                13,
                9
            ],
            "system_uwp": "B693688-5"
        },
        {
            "system_name": "Sagharr",
            "system_position": [
                14,
                6
            ],
            "system_uwp": "D633423-9"
        },
        {
            "system_name": "Urrgha",
            "system_position": [
                14,
                8
            ],
            "system_uwp": "X300000-0"
        },
        {
            "system_name": "Ovoeghagun",
            "system_position": [
                15,
                1
            ],
            "system_uwp": "E441300-2"
        },
        {
            "system_name": "Sighnarr",
            "system_position": [
                15,
                4
            ],
            "system_uwp": "B560576-C"
        },
        {
            "system_name": "Ghadzarrgh",
            "system_position": [
                15,
                6
            ],
            "system_uwp": "D4C1416-B"
        },
        {
            "system_name": "Dioco",
            "system_position": [
                16,
                2
            ],
            "system_uwp": "C4629EE-7"
        },
        {
            "system_name": "Sigurroegh",
            "system_position": [
                16,
                4
            ],
            "system_uwp": "A86A687-C"
        },
        {
            "system_name": "Uta",
            "system_position": [
                16,
                8
            ],
            "system_uwp": "B636441-A"
        },
        {
            "system_name": "Ikgzoeroulurr",
            "system_position": [
                17,
                1
            ],
            "system_uwp": "X5A0000-0"
        },
        {
            "system_name": "Voeraghz",
            "system_position": [
                17,
                5
            ],
            "system_uwp": "A544573-D"
        },
        {
            "system_name": "Aekokago",
            "system_position": [
                17,
                7
            ],
            "system_uwp": "D578785-5"
        },
        {
            "system_name": "Ugar",
            "system_position": [
                18,
                1
            ],
            "system_uwp": "D200325-9"
        },
        {
            "system_name": "Lizashlik",
            "system_position": [
                18,
                6
            ],
            "system_uwp": "A593694-8"
        },
        {
            "system_name": "Lwynhy",
            "system_position": [
                18,
                7
            ],
            "system_uwp": "C545988-9"
        },
        {
            "system_name": "Aladashumiiki",
            "system_position": [
                18,
                8
            ],
            "system_uwp": "C465975-6"
        },
        {
            "system_name": "Asihit",
            "system_position": [
                19,
                1
            ],
            "system_uwp": "D698534-6"
        },
        {
            "system_name": "Sovanjaak",
            "system_position": [
                19,
                2
            ],
            "system_uwp": "X400000-0"
        },
        {
            "system_name": "Kerkiilamu",
            "system_position": [
                19,
                3
            ],
            "system_uwp": "E210300-A"
        },
        {
            "system_name": "Pynuotkuos",
            "system_position": [
                19,
                6
            ],
            "system_uwp": "C6468A8-C"
        },
        {
            "system_name": "Ada",
            "system_position": [
                19,
                10
            ],
            "system_uwp": "C541999-5"
        },
        {
            "system_name": "Satih",
            "system_position": [
                20,
                3
            ],
            "system_uwp": "A658984-B"
        },
        {
            "system_name": "Naenaruel",
            "system_position": [
                20,
                4
            ],
            "system_uwp": "A5649B8-B"
        },
        {
            "system_name": "Rhonhi",
            "system_position": [
                20,
                5
            ],
            "system_uwp": "B4628B8-6"
        },
        {
            "system_name": "Ouzaell",
            "system_position": [
                20,
                7
            ],
            "system_uwp": "B433558-9"
        },
        {
            "system_name": "Aiwunupe",
            "system_position": [
                21,
                1
            ],
            "system_uwp": "C6978A6-5"
        },
        {
            "system_name": "Udkhaaziirash",
            "system_position": [
                21,
                2
            ],
            "system_uwp": "A7779DE-B"
        },
        {
            "system_name": "Mohy",
            "system_position": [
                21,
                3
            ],
            "system_uwp": "A4588DC-7"
        },
        {
            "system_name": "Gzodaegdoedz",
            "system_position": [
                21,
                4
            ],
            "system_uwp": "D443232-7"
        },
        {
            "system_name": "Ek",
            "system_position": [
                21,
                7
            ],
            "system_uwp": "X000000-0"
        },
        {
            "system_name": "Lykukihavyt",
            "system_position": [
                22,
                3
            ],
            "system_uwp": "C533458-8"
        },
        {
            "system_name": "Gumushu",
            "system_position": [
                22,
                4
            ],
            "system_uwp": "C682753-6"
        },
        {
            "system_name": "Kigaakigum",
            "system_position": [
                22,
                5
            ],
            "system_uwp": "D556768-2"
        },
        {
            "system_name": "Ychmiwryr",
            "system_position": [
                22,
                9
            ],
            "system_uwp": "B999510-C"
        },
        {
            "system_name": "Dusa",
            "system_position": [
                23,
                2
            ],
            "system_uwp": "C322545-9"
        },
        {
            "system_name": "Maga",
            "system_position": [
                23,
                3
            ],
            "system_uwp": "A675640-C"
        },
        {
            "system_name": "Gagiizidiiga",
            "system_position": [
                23,
                5
            ],
            "system_uwp": "C586786-6"
        },
        {
            "system_name": "Mor",
            "system_position": [
                23,
                10
            ],
            "system_uwp": "B996421-A"
        },
        {
            "system_name": "Amimuum",
            "system_position": [
                24,
                3
            ],
            "system_uwp": "C84797A-8"
        },
        {
            "system_name": "Oudhuegvae",
            "system_position": [
                24,
                5
            ],
            "system_uwp": "C625448-7"
        },
        {
            "system_name": "Argag",
            "system_position": [
                24,
                6
            ],
            "system_uwp": "E432656-7"
        },
        {
            "system_name": "Kumakiiga",
            "system_position": [
                24,
                8
            ],
            "system_uwp": "A988642-B"
        },
        {
            "system_name": "Ghersong",
            "system_position": [
                24,
                10
            ],
            "system_uwp": "A4536A9-A"
        },
        {
            "system_name": "Nuri",
            "system_position": [
                25,
                1
            ],
            "system_uwp": "D571200-7"
        },
        {
            "system_name": "Dekeli",
            "system_position": [
                25,
                3
            ],
            "system_uwp": "C775553-9"
        },
        {
            "system_name": "Resopem",
            "system_position": [
                25,
                4
            ],
            "system_uwp": "B8849BC-B"
        },
        {
            "system_name": "Maa",
            "system_position": [
                25,
                8
            ],
            "system_uwp": "C428538-9"
        },
        {
            "system_name": "Ullizo",
            "system_position": [
                26,
                5
            ],
            "system_uwp": "AA7799B-A"
        },
        {
            "system_name": "Farraghufueka",
            "system_position": [
                26,
                6
            ],
            "system_uwp": "B473755-7"
        },
        {
            "system_name": "Uekhoeng",
            "system_position": [
                26,
                7
            ],
            "system_uwp": "D510539-A"
        },
        {
            "system_name": "Sefinar",
            "system_position": [
                26,
                10
            ],
            "system_uwp": "D434443-8"
        },
        {
            "system_name": "Enoggvokhs",
            "system_position": [
                27,
                1
            ],
            "system_uwp": "D544542-6"
        },
        {
            "system_name": "Benadd",
            "system_position": [
                27,
                2
            ],
            "system_uwp": "A441631-8"
        },
        {
            "system_name": "Gvueruk",
            "system_position": [
                27,
                3
            ],
            "system_uwp": "E552438-9"
        },
        {
            "system_name": "Khefs Dzo",
            "system_position": [
                27,
                4
            ],
            "system_uwp": "A569989-8"
        },
        {
            "system_name": "Daegthor",
            "system_position": [
                27,
                5
            ],
            "system_uwp": "X300000-0"
        },
        {
            "system_name": "Naddes",
            "system_position": [
                27,
                9
            ],
            "system_uwp": "C554441-8"
        },
        {
            "system_name": "Lupushshir",
            "system_position": [
                28,
                5
            ],
            "system_uwp": "B7979EF-8"
        },
        {
            "system_name": "Vy",
            "system_position": [
                28,
                9
            ],
            "system_uwp": "B545625-9"
        },
        {
            "system_name": "Udenga",
            "system_position": [
                29,
                2
            ],
            "system_uwp": "X120000-0"
        },
        {
            "system_name": "Regu",
            "system_position": [
                29,
                7
            ],
            "system_uwp": "B000686-B"
        },
        {
            "system_name": "Gagur",
            "system_position": [
                29,
                8
            ],
            "system_uwp": "D647877-8"
        },
        {
            "system_name": "Raroota",
            "system_position": [
                29,
                10
            ],
            "system_uwp": "C610514-A"
        },
        {
            "system_name": "Aerrggeng",
            "system_position": [
                30,
                2
            ],
            "system_uwp": "A526665-B"
        },
        {
            "system_name": "Ibugug",
            "system_position": [
                30,
                3
            ],
            "system_uwp": "E554436-3"
        },
        {
            "system_name": "Urnaakashig",
            "system_position": [
                30,
                5
            ],
            "system_uwp": "E6A2321-B"
        },
        {
            "system_name": "Oneluevueknou",
            "system_position": [
                30,
                7
            ],
            "system_uwp": "A6569DG-7"
        },
        {
            "system_name": "Terkpedherhi",
            "system_position": [
                30,
                9
            ],
            "system_uwp": "B679844-6"
        },
        {
            "system_name": "Er",
            "system_position": [
                31,
                1
            ],
            "system_uwp": "E447436-8"
        },
        {
            "system_name": "Gasuu",
            "system_position": [
                31,
                3
            ],
            "system_uwp": "B313640-7"
        },
        {
            "system_name": "Mukekis",
            "system_position": [
                31,
                5
            ],
            "system_uwp": "X100000-0"
        },
        {
            "system_name": "Mopetu",
            "system_position": [
                31,
                7
            ],
            "system_uwp": "B79588B-C"
        },
        {
            "system_name": "Kikashinnipi",
            "system_position": [
                31,
                8
            ],
            "system_uwp": "X500000-0"
        },
        {
            "system_name": "Okghuthtsuegh",
            "system_position": [
                32,
                2
            ],
            "system_uwp": "C435451-8"
        },
        {
            "system_name": "Pualemaski",
            "system_position": [
                32,
                3
            ],
            "system_uwp": "X110000-0"
        },
        {
            "system_name": "Egt",
            "system_position": [
                32,
                5
            ],
            "system_uwp": "A7969BA-B"
        },
        {
            "system_name": "Khaerong",
            "system_position": [
                32,
                8
            ],
            "system_uwp": "E498232-8"
        },
        {
            "system_name": "Leeteng",
            "system_position": [
                32,
                9
            ],
            "system_uwp": "C433424-B"
        },
        {
            "system_name": "Bat",
            "system_position": [
                32,
                10
            ],
            "system_uwp": "D430214-A"
        },
        {
            "system_name": "Imkha",
            "system_position": [
                1,
                16
            ],
            "system_uwp": "C547420-6"
        },
        {
            "system_name": "Kulirzir",
            "system_position": [
                1,
                19
            ],
            "system_uwp": "X540000-0"
        },
        {
            "system_name": "Gisanal",
            "system_position": [
                2,
                11
            ],
            "system_uwp": "A778778-7"
        },
        {
            "system_name": "Kaspur",
            "system_position": [
                2,
                13
            ],
            "system_uwp": "D437438-9"
        },
        {
            "system_name": "Aedzae",
            "system_position": [
                3,
                13
            ],
            "system_uwp": "C692745-6"
        },
        {
            "system_name": "Zoegaekhso",
            "system_position": [
                4,
                11
            ],
            "system_uwp": "D438344-9"
        },
        {
            "system_name": "Garfaerroe",
            "system_position": [
                4,
                14
            ],
            "system_uwp": "C55888B-A"
        },
        {
            "system_name": "Khoengkuerrgh",
            "system_position": [
                4,
                16
            ],
            "system_uwp": "X100000-0"
        },
        {
            "system_name": "Agusha",
            "system_position": [
                4,
                17
            ],
            "system_uwp": "E649315-C"
        },
        {
            "system_name": "Bikali",
            "system_position": [
                5,
                18
            ],
            "system_uwp": "B5977AB-5"
        },
        {
            "system_name": "Kongrougzog",
            "system_position": [
                5,
                19
            ],
            "system_uwp": "A567ADF-7"
        },
        {
            "system_name": "Orrgorkso",
            "system_position": [
                6,
                11
            ],
            "system_uwp": "A63A310-C"
        },
        {
            "system_name": "Umanirgilunud",
            "system_position": [
                6,
                19
            ],
            "system_uwp": "X210000-0"
        },
        {
            "system_name": "Kungangfuk",
            "system_position": [
                7,
                11
            ],
            "system_uwp": "D3244BA-A"
        },
        {
            "system_name": "Kfodha",
            "system_position": [
                7,
                15
            ],
            "system_uwp": "A883997-B"
        },
        {
            "system_name": "Dakanikiguri",
            "system_position": [
                7,
                16
            ],
            "system_uwp": "B47255A-B"
        },
        {
            "system_name": "Anweg",
            "system_position": [
                7,
                18
            ],
            "system_uwp": "C79749A-9"
        },
        {
            "system_name": "Ivavours",
            "system_position": [
                8,
                11
            ],
            "system_uwp": "E453536-A"
        },
        {
            "system_name": "Kirralimigag",
            "system_position": [
                8,
                20
            ],
            "system_uwp": "CAA685B-B"
        },
        {
            "system_name": "Ellong",
            "system_position": [
                9,
                11
            ],
            "system_uwp": "C553555-6"
        },
        {
            "system_name": "Dhartsun",
            "system_position": [
                9,
                12
            ],
            "system_uwp": "B9899CA-D"
        },
        {
            "system_name": "Rumaaire",
            "system_position": [
                10,
                14
            ],
            "system_uwp": "X310000-0"
        },
        {
            "system_name": "Turrdun",
            "system_position": [
                10,
                16
            ],
            "system_uwp": "B647766-9"
        },
        {
            "system_name": "Talrotis",
            "system_position": [
                11,
                13
            ],
            "system_uwp": "X310000-0"
        },
        {
            "system_name": "Kikigulagabi",
            "system_position": [
                11,
                14
            ],
            "system_uwp": "B669576-7"
        },
        {
            "system_name": "Isgakikuga",
            "system_position": [
                11,
                18
            ],
            "system_uwp": "A8C5AA8-B"
        },
        {
            "system_name": "Kha",
            "system_position": [
                11,
                19
            ],
            "system_uwp": "C460A98-B"
        },
        {
            "system_name": "Keiwhi",
            "system_position": [
                12,
                13
            ],
            "system_uwp": "E513100-A"
        },
        {
            "system_name": "Suth",
            "system_position": [
                13,
                13
            ],
            "system_uwp": "A8B3667-B"
        },
        {
            "system_name": "Thigz",
            "system_position": [
                13,
                19
            ],
            "system_uwp": "A7569DC-B"
        },
        {
            "system_name": "Saamedirer",
            "system_position": [
                14,
                15
            ],
            "system_uwp": "B446556-D"
        },
        {
            "system_name": "Gaada",
            "system_position": [
                15,
                14
            ],
            "system_uwp": "B9A7346-C"
        },
        {
            "system_name": "Bamlisumguur",
            "system_position": [
                15,
                15
            ],
            "system_uwp": "A746759-A"
        },
        {
            "system_name": "Kotsfa",
            "system_position": [
                16,
                15
            ],
            "system_uwp": "B669977-A"
        },
        {
            "system_name": "Outoudzduez",
            "system_position": [
                16,
                16
            ],
            "system_uwp": "B659859-A"
        },
        {
            "system_name": "Omverendtto",
            "system_position": [
                16,
                17
            ],
            "system_uwp": "D6A5584-9"
        },
        {
            "system_name": "Cregen",
            "system_position": [
                17,
                15
            ],
            "system_uwp": "X200000-0"
        },
        {
            "system_name": "Postytos",
            "system_position": [
                17,
                18
            ],
            "system_uwp": "B56699D-9"
        },
        {
            "system_name": "Orrterz",
            "system_position": [
                18,
                16
            ],
            "system_uwp": "E478864-6"
        },
        {
            "system_name": "Kawahowhi",
            "system_position": [
                18,
                17
            ],
            "system_uwp": "E8B0338-A"
        },
        {
            "system_name": "Miorogrod",
            "system_position": [
                18,
                20
            ],
            "system_uwp": "A773620-9"
        },
        {
            "system_name": "Kesittanma",
            "system_position": [
                19,
                15
            ],
            "system_uwp": "A98A9BB-A"
        },
        {
            "system_name": "Nna",
            "system_position": [
                19,
                16
            ],
            "system_uwp": "X000000-0"
        },
        {
            "system_name": "Iriputanga",
            "system_position": [
                19,
                17
            ],
            "system_uwp": "A587755-B"
        },
        {
            "system_name": "Lannieton",
            "system_position": [
                19,
                18
            ],
            "system_uwp": "X540000-0"
        },
        {
            "system_name": "Ul",
            "system_position": [
                20,
                13
            ],
            "system_uwp": "B52A587-D"
        },
        {
            "system_name": "Sharagirukis",
            "system_position": [
                20,
                16
            ],
            "system_uwp": "A774861-7"
        },
        {
            "system_name": "Diduddbas",
            "system_position": [
                20,
                19
            ],
            "system_uwp": "C310346-A"
        },
        {
            "system_name": "Dilushka",
            "system_position": [
                21,
                12
            ],
            "system_uwp": "C314300-A"
        },
        {
            "system_name": "Ghatsghaeg",
            "system_position": [
                21,
                13
            ],
            "system_uwp": "XAFA000-0"
        },
        {
            "system_name": "Khaekarr",
            "system_position": [
                21,
                15
            ],
            "system_uwp": "X000000-0"
        },
        {
            "system_name": "Ke",
            "system_position": [
                21,
                17
            ],
            "system_uwp": "B452300-7"
        },
        {
            "system_name": "He",
            "system_position": [
                21,
                20
            ],
            "system_uwp": "A462957-A"
        },
        {
            "system_name": "Repstotjijk",
            "system_position": [
                22,
                11
            ],
            "system_uwp": "A446869-C"
        },
        {
            "system_name": "Mepdiisharig",
            "system_position": [
                22,
                17
            ],
            "system_uwp": "B56398C-A"
        },
        {
            "system_name": "Brybintw",
            "system_position": [
                22,
                19
            ],
            "system_uwp": "B433889-7"
        },
        {
            "system_name": "Dimijn",
            "system_position": [
                23,
                11
            ],
            "system_uwp": "C554678-6"
        },
        {
            "system_name": "Dy",
            "system_position": [
                23,
                13
            ],
            "system_uwp": "A6979A7-B"
        },
        {
            "system_name": "Urki",
            "system_position": [
                23,
                15
            ],
            "system_uwp": "C30389E-7"
        },
        {
            "system_name": "Kunzikikunuza",
            "system_position": [
                23,
                16
            ],
            "system_uwp": "AA6A98A-D"
        },
        {
            "system_name": "All",
            "system_position": [
                23,
                17
            ],
            "system_uwp": "C487434-8"
        },
        {
            "system_name": "Arraegue",
            "system_position": [
                23,
                18
            ],
            "system_uwp": "B541233-9"
        },
        {
            "system_name": "Oghaers",
            "system_position": [
                23,
                19
            ],
            "system_uwp": "A857988-D"
        },
        {
            "system_name": "Updashidiram",
            "system_position": [
                24,
                12
            ],
            "system_uwp": "A8799EA-A"
        },
        {
            "system_name": "Aenurrgaekou",
            "system_position": [
                24,
                15
            ],
            "system_uwp": "X8A2000-0"
        },
        {
            "system_name": "Mun",
            "system_position": [
                24,
                18
            ],
            "system_uwp": "C666968-6"
        },
        {
            "system_name": "Mutitoa",
            "system_position": [
                24,
                19
            ],
            "system_uwp": "X5A5000-0"
        },
        {
            "system_name": "Uirvrijn",
            "system_position": [
                25,
                14
            ],
            "system_uwp": "A77A863-C"
        },
        {
            "system_name": "Midishmumur",
            "system_position": [
                25,
                15
            ],
            "system_uwp": "C757566-3"
        },
        {
            "system_name": "Zoentuegh",
            "system_position": [
                25,
                18
            ],
            "system_uwp": "C556543-8"
        },
        {
            "system_name": "Nir",
            "system_position": [
                25,
                20
            ],
            "system_uwp": "C545576-8"
        },
        {
            "system_name": "Rwddffiar",
            "system_position": [
                26,
                17
            ],
            "system_uwp": "XAB3000-0"
        },
        {
            "system_name": "Iraad",
            "system_position": [
                26,
                19
            ],
            "system_uwp": "B777468-9"
        },
        {
            "system_name": "Akhgaeng",
            "system_position": [
                27,
                14
            ],
            "system_uwp": "A569989-C"
        },
        {
            "system_name": "Doeleir",
            "system_position": [
                29,
                11
            ],
            "system_uwp": "C5A4320-9"
        },
        {
            "system_name": "Deiddat",
            "system_position": [
                29,
                12
            ],
            "system_uwp": "B554963-9"
        },
        {
            "system_name": "Gjittnaeng",
            "system_position": [
                29,
                15
            ],
            "system_uwp": "AAC6668-9"
        },
        {
            "system_name": "Linajisme",
            "system_position": [
                29,
                18
            ],
            "system_uwp": "A788876-C"
        },
        {
            "system_name": "Taildahre",
            "system_position": [
                30,
                12
            ],
            "system_uwp": "B4569CG-B"
        },
        {
            "system_name": "Nuukhanir",
            "system_position": [
                30,
                15
            ],
            "system_uwp": "D324613-7"
        },
        {
            "system_name": "Di",
            "system_position": [
                30,
                17
            ],
            "system_uwp": "A477732-D"
        },
        {
            "system_name": "Iikhugama",
            "system_position": [
                30,
                18
            ],
            "system_uwp": "D482156-8"
        },
        {
            "system_name": "Manoaani",
            "system_position": [
                31,
                14
            ],
            "system_uwp": "C6889BD-6"
        },
        {
            "system_name": "Khii",
            "system_position": [
                31,
                15
            ],
            "system_uwp": "C42956A-9"
        },
        {
            "system_name": "Aeg",
            "system_position": [
                31,
                16
            ],
            "system_uwp": "C6847AD-6"
        },
        {
            "system_name": "Kiirkinkirizi",
            "system_position": [
                31,
                17
            ],
            "system_uwp": "A767978-D"
        },
        {
            "system_name": "Be",
            "system_position": [
                31,
                19
            ],
            "system_uwp": "C654645-4"
        },
        {
            "system_name": "Aeraegfoeksse",
            "system_position": [
                32,
                11
            ],
            "system_uwp": "B435412-D"
        },
        {
            "system_name": "Jaarut",
            "system_position": [
                32,
                13
            ],
            "system_uwp": "A7668A7-B"
        },
        {
            "system_name": "Ud",
            "system_position": [
                32,
                14
            ],
            "system_uwp": "B847741-7"
        },
        {
            "system_name": "Gviguezeghoug",
            "system_position": [
                32,
                15
            ],
            "system_uwp": "X000000-0"
        },
        {
            "system_name": "Viar",
            "system_position": [
                32,
                16
            ],
            "system_uwp": "C110401-C"
        },
        {
            "system_name": "Kimirii",
            "system_position": [
                32,
                17
            ],
            "system_uwp": "X100000-0"
        },
        {
            "system_name": "Agvarzoerr",
            "system_position": [
                32,
                19
            ],
            "system_uwp": "C540611-6"
        },
        {
            "system_name": "Nenn",
            "system_position": [
                1,
                21
            ],
            "system_uwp": "C64499E-8"
        },
        {
            "system_name": "Kuune",
            "system_position": [
                1,
                23
            ],
            "system_uwp": "A452A63-D"
        },
        {
            "system_name": "Mirashidi",
            "system_position": [
                1,
                24
            ],
            "system_uwp": "A66668B-8"
        },
        {
            "system_name": "Gzaek",
            "system_position": [
                2,
                23
            ],
            "system_uwp": "B97A562-C"
        },
        {
            "system_name": "Mar",
            "system_position": [
                3,
                28
            ],
            "system_uwp": "E653143-2"
        },
        {
            "system_name": "Thollydam",
            "system_position": [
                3,
                29
            ],
            "system_uwp": "X212000-0"
        },
        {
            "system_name": "Kokhs",
            "system_position": [
                4,
                29
            ],
            "system_uwp": "D410200-8"
        },
        {
            "system_name": "Sii",
            "system_position": [
                4,
                30
            ],
            "system_uwp": "D432100-9"
        },
        {
            "system_name": "Kuu",
            "system_position": [
                5,
                22
            ],
            "system_uwp": "B546875-B"
        },
        {
            "system_name": "Galiibegada",
            "system_position": [
                5,
                23
            ],
            "system_uwp": "D78A300-8"
        },
        {
            "system_name": "Ab",
            "system_position": [
                5,
                27
            ],
            "system_uwp": "B445569-7"
        },
        {
            "system_name": "Sing",
            "system_position": [
                6,
                22
            ],
            "system_uwp": "B566246-7"
        },
        {
            "system_name": "Gimashkhizara",
            "system_position": [
                6,
                23
            ],
            "system_uwp": "A76A88A-9"
        },
        {
            "system_name": "Pinapupiru",
            "system_position": [
                6,
                24
            ],
            "system_uwp": "B57657B-5"
        },
        {
            "system_name": "Fetap",
            "system_position": [
                6,
                27
            ],
            "system_uwp": "A458689-D"
        },
        {
            "system_name": "Temkaka",
            "system_position": [
                7,
                22
            ],
            "system_uwp": "A439679-A"
        },
        {
            "system_name": "Emug",
            "system_position": [
                7,
                23
            ],
            "system_uwp": "A97988B-8"
        },
        {
            "system_name": "Byddklob",
            "system_position": [
                7,
                24
            ],
            "system_uwp": "B998999-7"
        },
        {
            "system_name": "Le",
            "system_position": [
                7,
                28
            ],
            "system_uwp": "B663ACF-9"
        },
        {
            "system_name": "Whuuka",
            "system_position": [
                8,
                27
            ],
            "system_uwp": "X000000-0"
        },
        {
            "system_name": "Zasorrg",
            "system_position": [
                8,
                28
            ],
            "system_uwp": "C304442-B"
        },
        {
            "system_name": "Vun",
            "system_position": [
                9,
                22
            ],
            "system_uwp": "E68A100-7"
        },
        {
            "system_name": "Liadyhwed",
            "system_position": [
                9,
                23
            ],
            "system_uwp": "C693873-6"
        },
        {
            "system_name": "Ugwontfeidd",
            "system_position": [
                9,
                28
            ],
            "system_uwp": "A45798B-D"
        },
        {
            "system_name": "Arzan",
            "system_position": [
                10,
                24
            ],
            "system_uwp": "X541000-0"
        },
        {
            "system_name": "Keratapa",
            "system_position": [
                10,
                26
            ],
            "system_uwp": "B577223-9"
        },
        {
            "system_name": "Gulila",
            "system_position": [
                11,
                22
            ],
            "system_uwp": "C455484-6"
        },
        {
            "system_name": "Ston",
            "system_position": [
                11,
                24
            ],
            "system_uwp": "XAC7000-0"
        },
        {
            "system_name": "Rob",
            "system_position": [
                11,
                28
            ],
            "system_uwp": "X432000-0"
        },
        {
            "system_name": "Tipai",
            "system_position": [
                12,
                25
            ],
            "system_uwp": "A433677-C"
        },
        {
            "system_name": "Akhuranududi",
            "system_position": [
                12,
                26
            ],
            "system_uwp": "E656787-2"
        },
        {
            "system_name": "Milinkhi",
            "system_position": [
                12,
                27
            ],
            "system_uwp": "B775675-8"
        },
        {
            "system_name": "Ush",
            "system_position": [
                12,
                28
            ],
            "system_uwp": "A794A9B-A"
        },
        {
            "system_name": "Nidnalag",
            "system_position": [
                12,
                30
            ],
            "system_uwp": "X433000-0"
        },
        {
            "system_name": "Giapeimiwch",
            "system_position": [
                13,
                21
            ],
            "system_uwp": "X573000-0"
        },
        {
            "system_name": "Miirkha",
            "system_position": [
                13,
                22
            ],
            "system_uwp": "B323464-B"
        },
        {
            "system_name": "Gharrgh",
            "system_position": [
                13,
                23
            ],
            "system_uwp": "A7649ED-C"
        },
        {
            "system_name": "Sakimdurgani",
            "system_position": [
                13,
                28
            ],
            "system_uwp": "A673353-B"
        },
        {
            "system_name": "Ligish",
            "system_position": [
                13,
                29
            ],
            "system_uwp": "C777585-9"
        },
        {
            "system_name": "Gijrmerins",
            "system_position": [
                14,
                22
            ],
            "system_uwp": "D659156-9"
        },
        {
            "system_name": "Lasre",
            "system_position": [
                14,
                24
            ],
            "system_uwp": "A667872-8"
        },
        {
            "system_name": "Amli",
            "system_position": [
                14,
                25
            ],
            "system_uwp": "X100000-0"
        },
        {
            "system_name": "Iige",
            "system_position": [
                14,
                26
            ],
            "system_uwp": "X677000-0"
        },
        {
            "system_name": "Katowuepe",
            "system_position": [
                15,
                22
            ],
            "system_uwp": "X648000-0"
        },
        {
            "system_name": "Dung",
            "system_position": [
                15,
                23
            ],
            "system_uwp": "C445267-5"
        },
        {
            "system_name": "Bednystek",
            "system_position": [
                15,
                24
            ],
            "system_uwp": "X100000-0"
        },
        {
            "system_name": "Ab",
            "system_position": [
                16,
                22
            ],
            "system_uwp": "B84A964-9"
        },
        {
            "system_name": "Tapaslan",
            "system_position": [
                17,
                22
            ],
            "system_uwp": "X444000-0"
        },
        {
            "system_name": "Dourrgh",
            "system_position": [
                21,
                25
            ],
            "system_uwp": "X548000-0"
        },
        {
            "system_name": "Slelerkinwest",
            "system_position": [
                24,
                21
            ],
            "system_uwp": "X657000-0"
        },
        {
            "system_name": "Koungue",
            "system_position": [
                28,
                24
            ],
            "system_uwp": "X7B5000-0"
        },
        {
            "system_name": "Wunsmook",
            "system_position": [
                29,
                21
            ],
            "system_uwp": "X668000-0"
        },
        {
            "system_name": "Sjin",
            "system_position": [
                1,
                35
            ],
            "system_uwp": "E423100-9"
        },
        {
            "system_name": "Uerzksasnoeth",
            "system_position": [
                1,
                36
            ],
            "system_uwp": "A749A96-C"
        },
        {
            "system_name": "Runggvoeknue",
            "system_position": [
                1,
                40
            ],
            "system_uwp": "B682897-7"
        },
        {
            "system_name": "Aengaze",
            "system_position": [
                2,
                31
            ],
            "system_uwp": "D684667-4"
        },
        {
            "system_name": "Kellgaekaedae",
            "system_position": [
                2,
                32
            ],
            "system_uwp": "X300000-0"
        },
        {
            "system_name": "Ungar",
            "system_position": [
                2,
                34
            ],
            "system_uwp": "A443630-C"
        },
        {
            "system_name": "Si",
            "system_position": [
                2,
                40
            ],
            "system_uwp": "C423300-9"
        },
        {
            "system_name": "Odzoez",
            "system_position": [
                3,
                31
            ],
            "system_uwp": "B694334-8"
        },
        {
            "system_name": "Shila",
            "system_position": [
                3,
                34
            ],
            "system_uwp": "A561844-8"
        },
        {
            "system_name": "Lluezdhouz",
            "system_position": [
                3,
                38
            ],
            "system_uwp": "C64A68A-7"
        },
        {
            "system_name": "Ulluell",
            "system_position": [
                4,
                31
            ],
            "system_uwp": "C300377-9"
        },
        {
            "system_name": "Gil",
            "system_position": [
                4,
                34
            ],
            "system_uwp": "A586999-B"
        },
        {
            "system_name": "Adar",
            "system_position": [
                4,
                35
            ],
            "system_uwp": "B789998-C"
        },
        {
            "system_name": "Adkamiiga",
            "system_position": [
                5,
                33
            ],
            "system_uwp": "X538000-0"
        },
        {
            "system_name": "Kehemirata",
            "system_position": [
                5,
                35
            ],
            "system_uwp": "A401424-A"
        },
        {
            "system_name": "Staree",
            "system_position": [
                6,
                33
            ],
            "system_uwp": "A545666-7"
        },
        {
            "system_name": "Tuil",
            "system_position": [
                6,
                36
            ],
            "system_uwp": "X460000-0"
        },
        {
            "system_name": "Aerzondag",
            "system_position": [
                6,
                37
            ],
            "system_uwp": "B7389DF-9"
        },
        {
            "system_name": "Aa",
            "system_position": [
                6,
                38
            ],
            "system_uwp": "B958000-6"
        },
        {
            "system_name": "Aache",
            "system_position": [
                6,
                39
            ],
            "system_uwp": "B6799AB-D"
        },
        {
            "system_name": "Rraeng",
            "system_position": [
                7,
                35
            ],
            "system_uwp": "A538999-C"
        },
        {
            "system_name": "Paukjatnik",
            "system_position": [
                7,
                36
            ],
            "system_uwp": "C89A7CF-8"
        },
        {
            "system_name": "Oruengzila",
            "system_position": [
                7,
                38
            ],
            "system_uwp": "A765ABB-D"
        },
        {
            "system_name": "Reng",
            "system_position": [
                8,
                32
            ],
            "system_uwp": "A748737-A"
        },
        {
            "system_name": "Talkemiejat",
            "system_position": [
                8,
                33
            ],
            "system_uwp": "A547668-A"
        },
        {
            "system_name": "Fathall",
            "system_position": [
                8,
                34
            ],
            "system_uwp": "A866ADE-9"
        },
        {
            "system_name": "Kid",
            "system_position": [
                8,
                35
            ],
            "system_uwp": "D799567-6"
        },
        {
            "system_name": "Iriir",
            "system_position": [
                8,
                37
            ],
            "system_uwp": "X53A000-0"
        },
        {
            "system_name": "Aegnueg",
            "system_position": [
                8,
                39
            ],
            "system_uwp": "A452520-9"
        },
        {
            "system_name": "Dwycawlowm",
            "system_position": [
                9,
                31
            ],
            "system_uwp": "X222000-0"
        },
        {
            "system_name": "Iririi",
            "system_position": [
                9,
                32
            ],
            "system_uwp": "X434000-0"
        },
        {
            "system_name": "Siirgikagigaa",
            "system_position": [
                9,
                34
            ],
            "system_uwp": "X000000-0"
        },
        {
            "system_name": "Stij",
            "system_position": [
                9,
                35
            ],
            "system_uwp": "A54577A-B"
        },
        {
            "system_name": "Dede",
            "system_position": [
                9,
                39
            ],
            "system_uwp": "A999648-A"
        },
        {
            "system_name": "U",
            "system_position": [
                10,
                33
            ],
            "system_uwp": "A446300-C"
        },
        {
            "system_name": "Unmakhimshim",
            "system_position": [
                10,
                35
            ],
            "system_uwp": "E545120-6"
        },
        {
            "system_name": "Khakuukhimka",
            "system_position": [
                10,
                38
            ],
            "system_uwp": "X200000-0"
        },
        {
            "system_name": "Beprannein",
            "system_position": [
                11,
                32
            ],
            "system_uwp": "X300000-0"
        },
        {
            "system_name": "Aerafa",
            "system_position": [
                11,
                40
            ],
            "system_uwp": "A66AABA-D"
        },
        {
            "system_name": "Mir",
            "system_position": [
                12,
                32
            ],
            "system_uwp": "C695223-8"
        },
        {
            "system_name": "Mudadiikadu",
            "system_position": [
                12,
                33
            ],
            "system_uwp": "X570000-0"
        },
        {
            "system_name": "Aegvenuth",
            "system_position": [
                12,
                34
            ],
            "system_uwp": "D439200-7"
        },
        {
            "system_name": "Ada",
            "system_position": [
                12,
                35
            ],
            "system_uwp": "A878447-B"
        },
        {
            "system_name": "Inadimkhishir",
            "system_position": [
                12,
                38
            ],
            "system_uwp": "X100000-0"
        },
        {
            "system_name": "Emimgadii",
            "system_position": [
                13,
                32
            ],
            "system_uwp": "X431257-5"
        },
        {
            "system_name": "Gakha",
            "system_position": [
                14,
                32
            ],
            "system_uwp": "X401000-0"
        },
        {
            "system_name": "Ashila",
            "system_position": [
                15,
                40
            ],
            "system_uwp": "B7857A9-9"
        },
        {
            "system_name": "Emuula",
            "system_position": [
                19,
                33
            ],
            "system_uwp": "X300000-0"
        },
        {
            "system_name": "Miimish",
            "system_position": [
                21,
                39
            ],
            "system_uwp": "X444000-0"
        },
        {
            "system_name": "Aabe",
            "system_position": [
                23,
                38
            ],
            "system_uwp": "X539000-0"
        },
        {
            "system_name": "Kewhukape",
            "system_position": [
                25,
                31
            ],
            "system_uwp": "X787000-0"
        },
        {
            "system_name": "Guuzi",
            "system_position": [
                25,
                38
            ],
            "system_uwp": "X428000-0"
        },
        {
            "system_name": "Khaa",
            "system_position": [
                29,
                34
            ],
            "system_uwp": "X564000-0"
        }
    ]
}
